Metadata-Version: 1.1
Name: limri
Version: 0.0.0
Summary: 
